#ifndef JAVA_CLASS_H_
#define JAVA_CLASS_H_

#include <inttypes.h>

enum CONSTANT_POOL_TAGS {
  CONSTANT_Class = 7,
  CONSTANT_Fieldref = 9,
  CONSTANT_Methodref = 10,
  CONSTANT_InterfaceMethodref = 11,
  CONSTANT_String = 8,
  CONSTANT_Integer = 3,
  CONSTANT_Float = 4,
  CONSTANT_Long = 5,
  CONSTANT_Double = 6,
  CONSTANT_NameAndType = 12,
  CONSTANT_Utf8 = 1,
  CONSTANT_MethodHandle = 15,
  CONSTANT_MethodType = 16,
  CONSTANT_InvokeDynamic = 18,
};

enum CLASS_ACCESS_FLAGS {
  CLASS_ACC_PUBLIC = 0x0001,
  CLASS_ACC_FINAL = 0x0010,
  CLASS_ACC_SUPER = 0x0020,
  CLASS_ACC_INTERFACE = 0x0200,
  CLASS_ACC_ABSTRACT = 0x0400,
  CLASS_ACC_SYNTHETIC = 0x1000,
  CLASS_ACC_ANNOTATION = 0x2000,
  CLASS_ACC_ENUM = 0x4000,
};

enum INNER_CLASS_ACCESS_FLAGS {
  INNER_CLASS_ACC_PUBLIC = 0x0001,
  INNER_CLASS_ACC_PRIVATE = 0x0002,
  INNER_CLASS_ACC_PROTECTED = 0x0004,
  INNER_CLASS_ACC_STATIC = 0x0008,
  INNER_CLASS_ACC_FINAL = 0x0010,
  INNER_CLASS_ACC_INTERFACE = 0x0200,
  INNER_CLASS_ACC_ABSTRACT = 0x0400,
  INNER_CLASS_ACC_SYNTHETIC = 0x1000,
  INNER_CLASS_ACC_ANNOTATION = 0x2000,
  INNER_CLASS_ACC_ENUM = 0x4000,
};

enum FIELD_ACCESS_FLAGS {
  FIELD_ACC_PUBLIC = 0x0001,
  FIELD_ACC_PRIVATE = 0x0002,
  FIELD_ACC_PROTECTED = 0x0004,
  FIELD_ACC_STATIC = 0x0008,
  FIELD_ACC_FINAL = 0x0010,
  FIELD_ACC_VOLATILE = 0x0040,
  FIELD_ACC_TRANSIENT = 0x0080,
  FIELD_ACC_SYNTHETIC = 0x1000,
  FIELD_ACC_ENUM = 0x4000,
};

enum METHOD_ACCESS_FLAGS {
  METHOD_ACC_PUBLIC = 0x0001,
  METHOD_ACC_PRIVATE = 0x0002,
  METHOD_ACC_PROTECTED = 0x0004,
  METHOD_ACC_STATIC = 0x0008,
  METHOD_ACC_FINAL = 0x0010,
  METHOD_ACC_SYNCHRONIZED = 0x0020,
  METHOD_ACC_BRIDGE = 0x0040,
  METHOD_ACC_VARARGS = 0x0080,
  METHOD_ACC_NATIVE = 0x0100,
  METHOD_ACC_ABSTRACT = 0x0400,
  METHOD_ACC_STRICT = 0x0800,
  METHOD_ACC_SYNTHETIC = 0x1000,
};

enum CLASS_INST_OP {
  INST_NOP = 0x00,
  INST_ACONST_NULL = 0x01,
  INST_ICONST_M1 = 0x02,
  INST_ICONST_0 = 0x03,
  INST_ICONST_1 = 0x04,
  INST_ICONST_2 = 0x05,
  INST_ICONST_3 = 0x06,
  INST_ICONST_4 = 0x07,
  INST_ICONST_5 = 0x08,
  INST_LCONST_0 = 0x09,
  INST_LCONST_1 = 0x0a,
  INST_FCONST_0 = 0x0b,
  INST_FCONST_1 = 0x0c,
  INST_FCONST_2 = 0x0d,
  INST_DCONST_0 = 0x0e,
  INST_DCONST_1 = 0x0f,
  INST_BIPUSH = 0x10,
  INST_SIPUSH = 0x11,
  INST_LDC = 0x12,
  INST_LDC_W = 0x13,
  INST_LDC2_W = 0x14,
  INST_ILOAD = 0x15,
  INST_LLOAD = 0x16,
  INST_FLOAD = 0x17,
  INST_DLOAD = 0x18,
  INST_ALOAD = 0x19,
  INST_ILOAD_0 = 0x1a,
  INST_ILOAD_1 = 0x1b,
  INST_ILOAD_2 = 0x1c,
  INST_ILOAD_3 = 0x1d,
  INST_LLOAD_0 = 0x1e,
  INST_LLOAD_1 = 0x1f,
  INST_LLOAD_2 = 0x20,
  INST_LLOAD_3 = 0x21,
  INST_FLOAD_0 = 0x22,
  INST_FLOAD_1 = 0x23,
  INST_FLOAD_2 = 0x24,
  INST_FLOAD_3 = 0x25,
  INST_DLOAD_0 = 0x26,
  INST_DLOAD_1 = 0x27,
  INST_DLOAD_2 = 0x28,
  INST_DLOAD_3 = 0x29,
  INST_ALOAD_0 = 0x2a,
  INST_ALOAD_1 = 0x2b,
  INST_ALOAD_2 = 0x2c,
  INST_ALOAD_3 = 0x2d,
  INST_IALOAD = 0x2e,
  INST_LALOAD = 0x2f,
  INST_FALOAD = 0x30,
  INST_DALOAD = 0x31,
  INST_AALOAD = 0x32,
  INST_BALOAD = 0x33,
  INST_CALOAD = 0x34,
  INST_SALOAD = 0x35,
  INST_ISTORE = 0x36,
  INST_LSTORE = 0x37,
  INST_FSTORE = 0x38,
  INST_DSTORE = 0x39,
  INST_ASTORE = 0x3a,
  INST_ISTORE_0 = 0x3b,
  INST_ISTORE_1 = 0x3c,
  INST_ISTORE_2 = 0x3d,
  INST_ISTORE_3 = 0x3e,
  INST_LSTORE_0 = 0x3f,
  INST_LSTORE_1 = 0x40,
  INST_LSTORE_2 = 0x41,
  INST_LSTORE_3 = 0x42,
  INST_FSTORE_0 = 0x43,
  INST_FSTORE_1 = 0x44,
  INST_FSTORE_2 = 0x45,
  INST_FSTORE_3 = 0x46,
  INST_DSTORE_0 = 0x47,
  INST_DSTORE_1 = 0x48,
  INST_DSTORE_2 = 0x49,
  INST_DSTORE_3 = 0x4a,
  INST_ASTORE_0 = 0x4b,
  INST_ASTORE_1 = 0x4c,
  INST_ASTORE_2 = 0x4d,
  INST_ASTORE_3 = 0x4e,
  INST_IASTORE = 0x4f,
  INST_LASTORE = 0x50,
  INST_FASTORE = 0x51,
  INST_DASTORE = 0x52,
  INST_AASTORE = 0x53,
  INST_BASTORE = 0x54,
  INST_CASTORE = 0x55,
  INST_SASTORE = 0x56,
  INST_POP = 0x57,
  INST_POP2 = 0x58,
  INST_DUP = 0x59,
  INST_DUP_X1 = 0x5a,
  INST_DUP_X2 = 0x5b,
  INST_DUP2 = 0x5c,
  INST_DUP2_X1 = 0x5d,
  INST_DUP2_X2 = 0x5e,
  INST_SWAP = 0x5f,
  INST_IADD = 0x60,
  INST_LADD = 0x61,
  INST_FADD = 0x62,
  INST_DADD = 0x63,
  INST_ISUB = 0x64,
  INST_LSUB = 0x65,
  INST_FSUB = 0x66,
  INST_DSUB = 0x67,
  INST_IMUL = 0x68,
  INST_LMUL = 0x69,
  INST_FMUL = 0x6a,
  INST_DMUL = 0x6b,
  INST_IDIV = 0x6c,
  INST_LDIV = 0x6d,
  INST_FDIV = 0x6e,
  INST_DDIV = 0x6f,
  INST_IREM = 0x70,
  INST_LREM = 0x71,
  INST_FREM = 0x72,
  INST_DREM = 0x73,
  INST_INEG = 0x74,
  INST_LNEG = 0x75,
  INST_FNEG = 0x76,
  INST_DNEG = 0x77,
  INST_ISHL = 0x78,
  INST_LSHL = 0x79,
  INST_ISHR = 0x7a,
  INST_LSHR = 0x7b,
  INST_IUSHR = 0x7c,
  INST_LUSHR = 0x7d,
  INST_IAND = 0x7e,
  INST_LAND = 0x7f,
  INST_IOR = 0x80,
  INST_LOR = 0x81,
  INST_IXOR = 0x82,
  INST_LXOR = 0x83,
  INST_IINC = 0x84,
  INST_I2L = 0x85,
  INST_I2F = 0x86,
  INST_I2D = 0x87,
  INST_L2I = 0x88,
  INST_L2F = 0x89,
  INST_L2D = 0x8a,
  INST_F2I = 0x8b,
  INST_F2L = 0x8c,
  INST_F2D = 0x8d,
  INST_D2I = 0x8e,
  INST_D2L = 0x8f,
  INST_D2F = 0x90,
  INST_I2B = 0x91,
  INST_I2C = 0x92,
  INST_I2S = 0x93,
  INST_LCMP = 0x94,
  INST_FCMPL = 0x95,
  INST_FCMPG = 0x96,
  INST_DCMPL = 0x97,
  INST_DCMPG = 0x98,
  INST_IFEQ = 0x99,
  INST_IFNE = 0x9a,
  INST_IFLT = 0x9b,
  INST_IFGE = 0x9c,
  INST_IFGT = 0x9d,
  INST_IFLE = 0x9e,
  INST_IF_ICMPEQ = 0x9f,
  INST_IF_ICMPNE = 0xa0,
  INST_IF_ICMPLT = 0xa1,
  INST_IF_ICMPGE = 0xa2,
  INST_IF_ICMPGT = 0xa3,
  INST_IF_ICMPLE = 0xa4,
  INST_IF_ACMPEQ = 0xa5,
  INST_IF_ACMPNE = 0xa6,
  INST_GOTO = 0xa7,
  INST_JSR = 0xa8,
  INST_RET = 0xa9,
  INST_TABLESWITCH = 0xaa,
  INST_LOOKUPSWITCH = 0xab,
  INST_IRETURN = 0xac,
  INST_LRETURN = 0xad,
  INST_FRETURN = 0xae,
  INST_DRETURN = 0xaf,
  INST_ARETURN = 0xb0,
  INST_RETURN = 0xb1,
  INST_GETSTATIC = 0xb2,
  INST_PUTSTATIC = 0xb3,
  INST_GETFIELD = 0xb4,
  INST_PUTFIELD = 0xb5,
  INST_INVOKEVIRTUAL = 0xb6,
  INST_INVOKESPECIAL = 0xb7,
  INST_INVOKESTATIC = 0xb8,
  INST_INVOKEINTERFACE = 0xb9,
  INST_INVOKEDYNAMIC = 0xba,
  INST_NEW = 0xbb,
  INST_NEWARRAY = 0xbc,
  INST_ANEWARRAY = 0xbd,
  INST_ARRAYLENGTH = 0xbe,
  INST_ATHROW = 0xbf,
  INST_CHECKCAST = 0xc0,
  INST_INSTANCEOF = 0xc1,
  INST_MONITORENTER = 0xc2,
  INST_MONITOREXIT = 0xc3,
  INST_WIDE = 0xc4,
  INST_MULTIANEWARRAY = 0xc5,
  INST_IFNULL = 0xc6,
  INST_IFNONNULL = 0xc7,
  INST_GOTO_W = 0xc8,
  INST_JSR_W = 0xc9,
};

enum CLASS_INST_ARRAY_TYPE {
    T_BOOLEAN = 4,
    T_CHAR = 5,
    T_FLOAT = 6,
    T_DOUBLE = 7,
    T_BYTE = 8,
    T_SHORT = 9,
    T_INT = 10,
    T_LONG = 11,
};

enum VERIFICATION_TYPE {
  ITEM_Top = 0,
  ITEM_Integer = 1,
  ITEM_Float = 2,
  ITEM_Double = 3,
  ITEM_Long = 4,
  ITEM_Null = 5,
  ITEM_UninitializedThis = 6,
  ITEM_Object = 7,
  ITEM_Uninitialized = 8,
};

#endif  // JAVA_CLASS_H_
